{

     "com.ismail.fbsave":{
          "user_server":false,
          "server_url":"https://goapi.mzgs.net/server-facebook",
           "safe":1.3,
          "LIMIT":9,
          "products":["fb_weekly","fb_lifetime"],
          "products_discount":["fb_weekly_discount","fb_yearly_discount"],
          "show_native_ads":true,
          "showDiscountAfterPaywall":true,
          "buttonTrialText":"Try for $0.00",
        "buttonTrialText2":"Start Your Free Trial",
        "show_product_title_custom":true,
          "price_text_type":"unit",
          "show_paywall_on_find":true
          
     },
     
     "com.ismail.aistorygenerator": {
        "products": [
            "story_weekly",
            "story_yearly"
        ],
        "showDiscountAfterPaywall":true,       
        "limit":0,       
        "buttonTrialText":"Try for $0.00",
        "buttonTrialText2":"Start Your Free Trial"
    },
    "com.ismail.ainote": {
         "products": [
            "note_weekly",
            "note_lifetime"
        ],
         "products_discount": [
            "note_weekly_discount",
            "note_yearly_discount"
        ],
        "showDiscountAfterPaywall":true,       
        "limit":3,
        "subtitle_url":"http://87.106.86.41:9002/transcript",       
        "buttonTrialText":"Try for $0.00",
        "buttonTrialText2":"Start Your Free Trial"
    },
    "com.ismail.authenticatorapp": {
         "products": [
            "auth_weekly",
             "authenticator_lifetime"
            
        ],
         "products_discount": [
            "auth_weekly_discount",
            "auth_yearly_discount"
        ],
        "rate":1,
        "limit":3,
         "productTitleSuffix":"",
         "show3DaysInTrialTitle":true,
         "show3DyasFreeLabel":false,
        "showImageInPaywall":false,
         "paywallTiralTitle":"Try premium features for free",
         "paywallNormalTitle":"Upgrade for Unlimited Access",
        "buttonTrialText":"Try for $0.00",
        "buttonTrialText2":"Start Your Free Trial",
        "showDiscountAfterPaywall":true,
        "show_product_title_custom":true
    },
    "6474788506": {
        "app": "Habit Tracker",
        "SHOW_ADS": true,
        "HABIT_LIMIT": 2,
        "REPORT_LIMIT": 1
    },
    "com.ismail.habittracker": {
        "app": "Habit Tracker",
        "SHOW_ADS": true,
        "HABIT_LIMIT": 2,
        "REPORT_LIMIT": 1,
        "trialProduct": "habit_weekly_discount33",
        "products": [
            "habit_weekly_discount",
            "habit_yearly_discount"
        ],
        "selectedProduct": "habit_weekly_discount",
        "premiumTitle": "Try Premium Free",
        "buttonText": "START 3-DAY FREE TRIAL",
        "showFree3dayInfo": false
    },
    "com.ismail.backgroundremover": {
        "showImageInPaywall": false,
        "premiumTitle": "Unlimited Access To All Features",
        "buttonText": "Continue",
        "DAILY_LIMIT": 7,
        "inapprate_count": 1,
        "products": [
            "bgremover_weekly",
            "bgremover_lifetime"
        ],
        "selectedProduct": "bgremover_weekly"
    }
}
